design.v
module sha256_core(
    input clk, //clock signal
    input rst, //active high reset
    input [511:0] data_in, //512-bit input block
    output reg [255:0] hash_out //256-bit output block
);

    //internal state registers
    reg [31:0] A, B, C, D, E, F, G, H; //state variables
    reg [31:0] W [0:63]; //message schedule
    reg [31:0] K [0:63]; //round constants
    reg [5:0] round; //round counter
    reg [3:0] stage; //pipeline stage counter
    reg [31:0] T1, T2;

    //sha 256 round constants (Kt)
    //copying from pre prepared document
    initial begin
      K[0]  = 32'h428a2f98;
      K[1]  = 32'h71374491;
      K[2]  = 32'hb5c0fbcf; 
      K[3]  = 32'he9b5dba5;
      K[4]  = 32'h3956c25b;
      K[5]  = 32'h59f111f1;
      K[6]  = 32'h923f82a4;
      K[7]  = 32'hab1c5ed5;
      K[8]  = 32'hd807aa98;
      K[9]  = 32'h12835b01;
      K[10] = 32'h243185be;
      K[11] = 32'h550c7dc3;
      K[12] = 32'h72be5d74;
      K[13] = 32'h80deb1fe;
      K[14] = 32'h9bdc06a7;
      K[15] = 32'hc19bf174;
      K[16] = 32'he49b69c1;
      K[17] = 32'hefbe4786;
      K[18] = 32'h0fc19dc6;
      K[19] = 32'h240ca1cc;
      K[20] = 32'h2de92c6f;
      K[21] = 32'h4a7484aa;
      K[22] = 32'h5cb0a9dc;
      K[23] = 32'h76f988da;
      K[24] = 32'h983e5152;
      K[25] = 32'ha831c66d;
      K[26] = 32'hb00327c8;
      K[27] = 32'hbf597fc7;
      K[28] = 32'hc6e00bf3;
      K[29] = 32'hd5a79147;
      K[30] = 32'h06ca6351;
      K[31] = 32'h14292967;
      K[32] = 32'h27b70a85;
      K[33] = 32'h2e1b2138;
      K[34] = 32'h4d2c6dfc;
      K[35] = 32'h53380d13;
      K[36] = 32'h650a7354;
      K[37] = 32'h766a0abb;
      K[38] = 32'h81c2c92e;
      K[39] = 32'h92722c85;
      K[40] = 32'ha2bfe8a1;
      K[41] = 32'ha81a664b;
      K[42] = 32'hc24b8b70;
      K[43] = 32'hc76c51a3;
      K[44] = 32'hd192e819;
      K[45] = 32'hd6990624;
      K[46] = 32'hf40e3585;
      K[47] = 32'h106aa070;
      K[48] = 32'h19a4c116;
      K[49] = 32'h1e376c08;
      K[50] = 32'h2748774c;
      K[51] = 32'h34b0bcb5;
      K[52] = 32'h391c0cb3;
      K[53] = 32'h4ed8aa4a;
      K[54] = 32'h5b9cca4f;
      K[55] = 32'h682e6ff3;
      K[56] = 32'h748f82ee;
      K[57] = 32'h78a5636f;
      K[58] = 32'h84c87814;
      K[59] = 32'h8cc70208;
      K[60] = 32'h90befffa;
      K[61] = 32'ha4506ceb;
      K[62] = 32'hbef9a3f7;
      K[63] = 32'hc67178f2;
    end

    //sha 256 functions
    function [31:0] Ch;
        input [31:0] x, y, z;
        begin
          Ch = (x & y) ^ (~x & z);
        end
    endfunction

    function [31:0] Maj;
        input [31:0] x, y, z;
        begin
          Maj = (x & y) ^ (x & z) ^ (y & z);
        end
    endfunction

    function [31:0] Sigma0;
        input [31:0] x;
        begin
          Sigma0 = {x[1:0], x[31:2]} ^ {x[12:0], x[31:13]} ^ {x[21:0], x[31:22]};
        end
    endfunction

    function [31:0] Sigma1;
        input [31:0] x;
        begin
          Sigma1 = {x[5:0], x[31:6]} ^ {x[10:0], x[31:11]} ^ {x[24:0], x[31:25]};
        end
    endfunction

    function [31:0] sigma0;
        input [31:0] x;
        begin
          sigma0 = {x[6:0], x[31:7]} ^ {x[17:0], x[31:18]} ^ {x >> 3};
        end
    endfunction

    function [31:0] sigma1;
        input [31:0] x;
        begin
          sigma1 = {x[16:0], x[31:17]} ^ {x[18:0], x[31:19]} ^ {x >> 10};
        end
    endfunction

    //message scheduling computation
    always @(posedge clk or posedge rst) begin
      if (rst) begin
        for (integer i = 0; i <64; i = i + 1) W[i] <= 0;
      end else begin
        for (integer i = 0; i < 16; i = i + 1) W[i] <= data_in[i*32 +: 32];
        for (integer i = 16; i < 64; i = i + 1) W[i] <= sigma1(W[i-2]) + W[i-7] + sigma0(W[i-15]) + W[i-16];
      end
    end

    //sha 256 compression function
    always @(posedge clk or posedge rst) begin
      if (rst) begin
        A <= 32'h6a09e667;
        B <= 32'hbb67ae85;
        C <= 32'h3c6ef372;
        D <= 32'ha54ff53a;
        E <= 32'h510e527f;
        F <= 32'h9b05688c;
        G <= 32'h1f83d9ab;
        H <= 32'h5be0cd19;
        round <= 0;
        stage <= 0;
      end else begin
        if (stage < 10) begin
          //perform 6-7 rounds per stage
          for (integer i = 0; i < 6; i = i + 1) begin
            if (round < 64) begin
              T1 = H + Sigma1(E) + Ch(E, F, G) + K[round] + W[round];
              T2 = Sigma0(A) + Maj(A, B, C);
              H <= G;
              G <= F;
              F <= E;
              E <= D + T1;
              D <= C;
              C <= B;
              B <= A;
              A <= T1 + T2;
              round <= round + 1;
            end
          end
          stage <= stage + 1;
        end else begin
          //final hash output
          hash_out <= {A, B, C, D, E, F, G, H};
        end
      end
    end

endmodule

testbench.v
module sha256_tb();

    reg clk;
    reg rst;
    reg [511:0] data_in;
    wire [255:0] hash_out;

    //instantiate the sha256 core
    sha256_core uut(
        .clk(clk),
        .rst(rst),
        .data_in(data_in),
        .hash_out(hash_out)
    );

    //clock generation
    initial begin
      clk = 0;
      forever #5 clk = ~clk;
    end

    //test vector from fips pub 180-4
    initial begin
      rst = 1;
      data_in = 512'h61626380000000000000000000000000000000000000000000000000000000000000000000000000000000000000000000000000000000000000000000000018;
      #20; // wait for reset
      rst = 0;
      #110; //processing
      $display("Hash Output: %h", hash_out);
      #300;
      $finish;
    end

    initial begin
      $dumpfile("dump.vcd");
      $dumpvars(0);
    end

endmodule

dump.vcd
$date
	Tue Feb 04 17:48:05 2025
$end
$version
	Icarus Verilog
$end
$timescale
	1s
$end
$scope module sha256_tb $end
$var wire 256 ! hash_out [255:0] $end
$var reg 1 " clk $end
$var reg 512 # data_in [511:0] $end
$var reg 1 $ rst $end
$scope module uut $end
$var wire 1 " clk $end
$var wire 512 % data_in [511:0] $end
$var wire 1 $ rst $end
$var reg 32 & A [31:0] $end
$var reg 32 ' B [31:0] $end
$var reg 32 ( C [31:0] $end
$var reg 32 ) D [31:0] $end
$var reg 32 * E [31:0] $end
$var reg 32 + F [31:0] $end
$var reg 32 , G [31:0] $end
$var reg 32 - H [31:0] $end
$var reg 32 . T1 [31:0] $end
$var reg 32 / T2 [31:0] $end
$var reg 256 0 hash_out [255:0] $end
$var reg 6 1 round [5:0] $end
$var reg 4 2 stage [3:0] $end
$scope function Ch $end
$var reg 32 3 x [31:0] $end
$var reg 32 4 y [31:0] $end
$var reg 32 5 z [31:0] $end
$upscope $end
$scope function Maj $end
$var reg 32 6 x [31:0] $end
$var reg 32 7 y [31:0] $end
$var reg 32 8 z [31:0] $end
$upscope $end
$scope function Sigma0 $end
$var reg 32 9 x [31:0] $end
$upscope $end
$scope function Sigma1 $end
$var reg 32 : x [31:0] $end
$upscope $end
$scope function sigma0 $end
$var reg 32 ; x [31:0] $end
$upscope $end
$scope function sigma1 $end
$var reg 32 < x [31:0] $end
$upscope $end
$scope begin $ivl_for_loop0 $end
$var integer 32 = i [31:0] $end
$upscope $end
$scope begin $ivl_for_loop1 $end
$var integer 32 > i [31:0] $end
$upscope $end
$scope begin $ivl_for_loop2 $end
$var integer 32 ? i [31:0] $end
$upscope $end
$scope begin $ivl_for_loop3 $end
$var integer 32 @ i [31:0] $end
$upscope $end
$upscope $end
$upscope $end
$enddefinitions $end
$comment Show the parameter values. $end
$dumpall
$end
#0
$dumpvars
bx @
bx ?
bx >
b1000000 =
bx <
bx ;
bx :
bx 9
bx 8
bx 7
bx 6
bx 5
bx 4
bx 3
b0 2
b0 1
bx 0
bx /
bx .
b1011011111000001100110100011001 -
b11111100000111101100110101011 ,
b10011011000001010110100010001100 +
b1010001000011100101001001111111 *
b10100101010011111111010100111010 )
b111100011011101111001101110010 (
b10111011011001111010111010000101 '
b1101010000010011110011001100111 &
b1100001011000100110001110000000000000000000000000000000000000000000000000000000000000000000000000000000000000000000000000000000000000000000000000000000000000000000000000000000000000000000000000000000000000000000000000000000000000000000000000000000000000000000000000000000000000000000000000000000000000000000000000000000000000000000000000000000000000000000000000000000000000000000000000000000000000000000000000000000000000000000000000000000000000000000000000000000000000000000000000000000000000000000000000011000 %
1$
b1100001011000100110001110000000000000000000000000000000000000000000000000000000000000000000000000000000000000000000000000000000000000000000000000000000000000000000000000000000000000000000000000000000000000000000000000000000000000000000000000000000000000000000000000000000000000000000000000000000000000000000000000000000000000000000000000000000000000000000000000000000000000000000000000000000000000000000000000000000000000000000000000000000000000000000000000000000000000000000000000000000000000000000000000011000 #
0"
bx !
$end
#5
b1000000 =
1"
#10
0"
#15
b1000000 =
1"
#20
0"
0$
#25
b1 2
b1 1
b11111100000010001000100001001101 &
b1101010000010011110011001100111 '
b10111011011001111010111010000101 (
b111100011011101111001101110010 )
b10011000110001111110001010100010 *
b1010001000011100101001001111111 +
b10011011000001010110100010001100 ,
b11111100000111101100110101011 -
b0 ;
b0 <
b1000000 ?
b10000 >
b1000100100001001101011100101 /
b1101010000010011110011001100111 6
b10111011011001111010111010000101 7
b111100011011101111001101110010 8
b1101010000010011110011001100111 9
b11110011011101111110110101101000 .
b1010001000011100101001001111111 3
b10011011000001010110100010001100 4
b11111100000111101100110101011 5
b1010001000011100101001001111111 :
b110 @
1"
#30
0"
#35
b10 2
b10 1
b1111010110110010110001010010000 &
b11111100000010001000100001001101 '
b1101010000010011110011001100111 (
b10111011011001111010111010000101 )
b10011101111100011011001000010110 *
b10011000110001111110001010100010 +
b1010001000011100101001001111111 ,
b10011011000001010110100010001100 -
b0 ;
b0 <
b1000000 ?
b10000 >
b11001010101101010001111101100 /
b11111100000010001000100001001101 6
b1101010000010011110011001100111 7
b10111011011001111010111010000101 8
b11111100000010001000100001001101 9
b1100001100000101011111010100100 .
b10011000110001111110001010100010 3
b1010001000011100101001001111111 4
b10011011000001010110100010001100 5
b10011000110001111110001010100010 :
b110 @
1"
#40
0"
#45
b11 2
b11 1
b11110011110111010110110000111111 &
b1111010110110010110001010010000 '
b11111100000010001000100001001101 (
b1101010000010011110011001100111 )
b11000101011110110110100011111011 *
b10011101111100011011001000010110 +
b10011000110001111110001010100010 ,
b1010001000011100101001001111111 -
b0 ;
b0 <
b1000000 ?
b10000 >
b11101001110010011011000111001001 /
b1111010110110010110001010010000 6
b11111100000010001000100001001101 7
b1101010000010011110011001100111 8
b1111010110110010110001010010000 9
b1010000100111011101001110110 .
b10011101111100011011001000010110 3
b10011000110001111110001010100010 4
b1010001000011100101001001111111 5
b10011101111100011011001000010110 :
b110 @
1"
#50
0"
#55
b100 2
b100 1
b1010001001001011000110101010 &
b11110011110111010110110000111111 '
b1111010110110010110001010010000 (
b11111100000010001000100001001101 )
b10010000100111001111010111001001 *
b11000101011110110110100011111011 +
b10011101111100011011001000010110 ,
b10011000110001111110001010100010 -
b0 ;
b0 <
b1000000 ?
b10000 >
b11100011100100011010001001001000 /
b11110011110111010110110000111111 6
b1111010110110010110001010010000 7
b11111100000010001000100001001101 8
b11110011110111010110110000111111 9
b100110100100110000111101100010 .
b11000101011110110110100011111011 3
b10011101111100011011001000010110 4
b10011000110001111110001010100010 5
b11000101011110110110100011111011 :
b110 @
1"
#60
0"
#65
b101 2
b101 1
b1001000100111111100001001111110 &
b1010001001001011000110101010 '
b11110011110111010110110000111111 (
b1111010110110010110001010010000 )
b101100101010110001010010101010 *
b10010000100111001111010111001001 +
b11000101011110110110100011111011 ,
b10011101111100011011001000010110 -
b100100000110110001101011100110 ;
b1011010101101100011111010111110 <
b1000000 ?
b10000 >
b10111111111010011011000100001 /
b1010001001001011000110101010 6
b11110011110111010110110000111111 7
b1111010110110010110001010010000 8
b1010001001001011000110101010 9
b110000101000101000110001011101 .
b10010000100111001111010111001001 3
b11000101011110110110100011111011 4
b10011101111100011011001000010110 5
b10010000100111001111010111001001 :
b110 @
1"
#70
0"
#75
b110 2
b110 1
b1101011101100101101101010000111 &
b1001000100111111100001001111110 '
b1010001001001011000110101010 (
b11110011110111010110110000111111 )
b10011101000100100000111110010110 *
b101100101010110001010010101010 +
b10010000100111001111010111001001 ,
b11000101011110110110100011111011 -
b100001110110001101000000010011 ;
b10010000111010111110101000010110 <
b1000000 ?
b10000 >
b1001001011110100010110110000001 /
b1001000100111111100001001111110 6
b1010001001001011000110101010 7
b11110011110111010110110000111111 8
b1001000100111111100001001111110 9
b100010001110001010110100000110 .
b101100101010110001010010101010 3
b10010000100111001111010111001001 4
b11000101011110110110100011111011 5
b101100101010110001010010101010 :
b110 @
1"
#80
0"
#85
b111 2
b111 1
b10010110010111101100101011100010 &
b1101011101100101101101010000111 '
b1001000100111111100001001111110 (
b1010001001001011000110101010 )
b1111001110001110110110111011010 *
b10011101000100100000111110010110 +
b101100101010110001010010101010 ,
b10010000100111001111010111001001 -
b100000010100111011011011001101 ;
b10111000101101100100111010111100 <
b1000000 ?
b10000 >
b10000011101001100100101000111 /
b1101011101100101101101010000111 6
b1001000100111111100001001111110 7
b1010001001001011000110101010 8
b1101011101100101101101010000111 9
b10000101111010100000000110011011 .
b10011101000100100000111110010110 3
b101100101010110001010010101010 4
b10010000100111001111010111001001 5
b10011101000100100000111110010110 :
b110 @
1"
#90
0"
#95
b1000 2
b1000 1
b1011110010010011000111110110011 &
b10010110010111101100101011100010 '
b1101011101100101101101010000111 (
b1001000100111111100001001111110 )
b10010100001001101110110001100000 *
b1111001110001110110110111011010 +
b10011101000100100000111110010110 ,
b101100101010110001010010101010 -
b100000010100111011011011001101 ;
b1011111100110110111100001100101 <
b1000000 ?
b10000 >
b11010100010001110101010011111101 /
b10010110010111101100101011100010 6
b1101011101100101101101010000111 7
b1001000100111111100001001111110 8
b10010110010111101100101011100010 9
b10001010000000100011101010110110 .
b1111001110001110110110111011010 3
b10011101000100100000111110010110 4
b101100101010110001010010101010 5
b1111001110001110110110111011010 :
b110 @
1"
#100
0"
#105
b1001 2
b1001 1
b100101100011101000010110111010 &
b1011110010010011000111110110011 '
b10010110010111101100101011100010 (
b1101011101100101101101010000111 )
b10000011100111010010000010111100 *
b10010100001001101110110001100000 +
b1111001110001110110110111011010 ,
b10011101000100100000111110010110 -
b1001010011001111001111110000 ;
b1000000001010100101010110011101 <
b1000000 ?
b10000 >
b11101010100100010010011101111100 /
b1011110010010011000111110110011 6
b10010110010111101100101011100010 7
b1101011101100101101101010000111 8
b1011110010010011000111110110011 9
b111010111111010101111000111110 .
b10010100001001101110110001100000 3
b1111001110001110110110111011010 4
b10011101000100100000111110010110 5
b10010100001001101110110001100000 :
b110 @
1"
#110
0"
#115
b1010 2
b1010 1
b10000111110111010010011010011110 &
b100101100011101000010110111010 '
b1011110010010011000111110110011 (
b10010110010111101100101011100010 )
b111110100111010000101111100111 *
b10000011100111010010000010111100 +
b10010100001001101110110001100000 ,
b1111001110001110110110111011010 -
b1100101111010011110110110001010 ;
b11111011111000010110010011000010 <
b1000000 ?
b10000 >
b10110100111100101111010100111110 /
b100101100011101000010110111010 6
b1011110010010011000111110110011 7
b10010110010111101100101011100010 8
b100101100011101000010110111010 9
b11010010111010100011000101100000 .
b10000011100111010010000010111100 3
b10010100001001101110110001100000 4
b1111001110001110110110111011010 5
b10000011100111010010000010111100 :
b110 @
1"
#120
0"
#125
b1000011111011101001001101001111000100101100011101000010110111010010111100100100110001111101100111001011001011110110010101110001000111110100111010000101111100111100000111001110100100000101111001001010000100110111011000110000001111001110001110110110111011010 !
b1000011111011101001001101001111000100101100011101000010110111010010111100100100110001111101100111001011001011110110010101110001000111110100111010000101111100111100000111001110100100000101111001001010000100110111011000110000001111001110001110110110111011010 0
b11110110110111011010101100000100 ;
b100001001101001101001101000011 <
b1000000 ?
b10000 >
1"
#130
0"
#135
b11100000100101000101101011100001 ;
b11110100101010000101111100111101 <
b1000000 ?
b10000 >
1"
#140
0"
#145
b11100000100101000101101011100001 ;
b10010010011101110011011111011000 <
b1000000 ?
b10000 >
1"
#150
0"
#155
b11000000010001101110101000110011 ;
b110000110100011001100011000010 <
b1000000 ?
b10000 >
1"
#160
0"
#165
b11000000010001101110101000110011 ;
b11011010000100100001010100110010 <
b1000000 ?
b10000 >
1"
#170
0"
#175
b1101011010100111011110110110100 ;
b10100001101001100110001000011011 <
b1000000 ?
b10000 >
1"
#180
0"
#185
b1101011010100111011110110110100 ;
b10100001101001100110001000011011 <
b1000000 ?
b10000 >
1"
#190
0"
#195
b1101011010100111011110110110100 ;
b10111110110110110000111011000000 <
b1000000 ?
b10000 >
1"
#200
0"
#205
b11110010001100100000001111010000 ;
b110011011010000010111110000111 <
b1000000 ?
b10000 >
1"
#210
0"
#215
b11110010001100100000001111010000 ;
b10101010100010110111101010111011 <
b1000000 ?
b10000 >
1"
#220
0"
#225
b11110010001100100000001111010000 ;
b10101010100010110111101010111011 <
b1000000 ?
b10000 >
1"
#230
0"
#235
b11110010001100100000001111010000 ;
b10101010100010110111101010111011 <
b1000000 ?
b10000 >
1"
#240
0"
#245
b11110010001100100000001111010000 ;
b1000001100110000111100111001101 <
b1000000 ?
b10000 >
1"
#250
0"
#255
b11110010001100100000001111010000 ;
b1000001100110000111100111001101 <
b1000000 ?
b10000 >
1"
#260
0"
#265
b11110010001100100000001111010000 ;
b11110101011001100101101000011110 <
b1000000 ?
b10000 >
1"
#270
0"
#275
b11110010001100100000001111010000 ;
b11110101011001100101101000011110 <
b1000000 ?
b10000 >
1"
#280
0"
#285
b11110010001100100000001111010000 ;
b11110101011001100101101000011110 <
b1000000 ?
b10000 >
1"
#290
0"
#295
b11110010001100100000001111010000 ;
b11110101011001100101101000011110 <
b1000000 ?
b10000 >
1"
#300
0"
#305
b11110010001100100000001111010000 ;
b11110101011001100101101000011110 <
b1000000 ?
b10000 >
1"
#310
0"
#315
b11110010001100100000001111010000 ;
b11110101011001100101101000011110 <
b1000000 ?
b10000 >
1"
#320
0"
#325
b11110010001100100000001111010000 ;
b11110101011001100101101000011110 <
b1000000 ?
b10000 >
1"
#330
0"
#335
b11110010001100100000001111010000 ;
b11110101011001100101101000011110 <
b1000000 ?
b10000 >
1"
#340
0"
#345
b11110010001100100000001111010000 ;
b11110101011001100101101000011110 <
b1000000 ?
b10000 >
1"
#350
0"
#355
b11110010001100100000001111010000 ;
b11110101011001100101101000011110 <
b1000000 ?
b10000 >
1"
#360
0"
#365
b11110010001100100000001111010000 ;
b11110101011001100101101000011110 <
b1000000 ?
b10000 >
1"
#370
0"
#375
b11110010001100100000001111010000 ;
b11110101011001100101101000011110 <
b1000000 ?
b10000 >
1"
#380
0"
#385
b11110010001100100000001111010000 ;
b11110101011001100101101000011110 <
b1000000 ?
b10000 >
1"
#390
0"
#395
b11110010001100100000001111010000 ;
b11110101011001100101101000011110 <
b1000000 ?
b10000 >
1"
#400
0"
#405
b11110010001100100000001111010000 ;
b11110101011001100101101000011110 <
b1000000 ?
b10000 >
1"
#410
0"
#415
b11110010001100100000001111010000 ;
b11110101011001100101101000011110 <
b1000000 ?
b10000 >
1"
#420
0"
#425
b11110010001100100000001111010000 ;
b11110101011001100101101000011110 <
b1000000 ?
b10000 >
1"
